{
  "gitSyncId": "670ac98e1d2c4329a60fb996_554416dd-26e1-4778-91e5-c0791f88c9c3",
  "id": "Orders_utils.handleCheckProduct",
  "pluginId": "js-plugin",
  "pluginType": "JS",
  "unpublishedAction": {
    "actionConfiguration": {
      "encodeParamsToggle": true,
      "isAsync": true,
      "jsArguments": [
        {
          "name": "currentItem"
        }
      ],
      "paginationType": "NONE",
      "timeoutInMillisecond": 10000
    },
    "collectionId": "Orders_utils",
    "confirmBeforeExecute": false,
    "datasource": {
      "isAutoGenerated": false,
      "name": "UNUSED_DATASOURCE",
      "pluginId": "js-plugin"
    },
    "dynamicBindingPathList": [
      {
        "key": "body"
      }
    ],
    "executeOnLoad": false,
    "fullyQualifiedName": "utils.handleCheckProduct",
    "name": "handleCheckProduct",
    "pageId": "Orders",
    "userSetOnLoad": false
  }
}