{
  "gitSyncId": "670ac98e1d2c4329a60fb996_57a0b0f5-ea48-472b-addf-2d94d994aa5a",
  "id": "Orders_utils.statusColor",
  "pluginId": "js-plugin",
  "pluginType": "JS",
  "unpublishedAction": {
    "actionConfiguration": {
      "encodeParamsToggle": true,
      "isAsync": false,
      "jsArguments": [
        {
          "name": "status"
        }
      ],
      "paginationType": "NONE",
      "timeoutInMillisecond": 10000
    },
    "collectionId": "Orders_utils",
    "confirmBeforeExecute": false,
    "datasource": {
      "isAutoGenerated": false,
      "name": "UNUSED_DATASOURCE",
      "pluginId": "js-plugin"
    },
    "dynamicBindingPathList": [
      {
        "key": "body"
      }
    ],
    "executeOnLoad": false,
    "fullyQualifiedName": "utils.statusColor",
    "name": "statusColor",
    "pageId": "Orders",
    "userSetOnLoad": false
  }
}